aws/__init__.py
aws/client.py
aws/config.py
aws/logz.py
aws/utils.py
awspydk-0.0.1.dist-info/LICENSE
awspydk-0.0.1.dist-info/METADATA
awspydk-0.0.1.dist-info/WHEEL
awspydk-0.0.1.dist-info/top_level.txt
awspydk-0.0.1.dist-info/RECORD
