Metadata-Version: 2.1
Name: awspydk
Version: 0.0.1
Summary: Dynamic Dataclasses for the Super Lazy
Home-page: https://github.com/trisongz/aws-sdk
Author: Tri Songz
Author-email: ts@growthengineai.com
License: MIT Style
Platform: UNKNOWN
Classifier: Intended Audience :: Developers
Classifier: License :: OSI Approved :: MIT License
Classifier: Programming Language :: Python :: 3.7
Classifier: Topic :: Software Development :: Libraries
License-File: LICENSE
Requires-Dist: boto3
Requires-Dist: lazycls
